CHANGES.rst
LICENSE
README.rst
setup.py
uspto/__init__.py
uspto/celery/__init__.py
uspto/celery/app.py
uspto/celery/tasks.py
uspto/pbd/__init__.py
uspto/pbd/client.py
uspto/pbd/command.py
uspto/pbd/document.py
uspto/pbd/tasks.py
uspto/peds/__init__.py
uspto/peds/client.py
uspto/peds/command.py
uspto/peds/document.py
uspto/peds/tasks.py
uspto/util/__init__.py
uspto/util/client.py
uspto/util/command.py
uspto/util/common.py
uspto/util/document.py
uspto/util/numbers.py
uspto/util/tasks.py
uspto_opendata_python.egg-info/PKG-INFO
uspto_opendata_python.egg-info/SOURCES.txt
uspto_opendata_python.egg-info/dependency_links.txt
uspto_opendata_python.egg-info/entry_points.txt
uspto_opendata_python.egg-info/not-zip-safe
uspto_opendata_python.egg-info/requires.txt
uspto_opendata_python.egg-info/top_level.txt