Metadata-Version: 2.1
Name: uspto-opendata-python
Version: 0.8.1
Summary: uspto-opendata-python is a client library for accessing the USPTO Open Data APIs
Home-page: https://github.com/ip-tools/uspto-opendata-python
Author: Andreas Motl
Author-email: andreas.motl@ip-tools.org
License: MIT
Keywords: uspto pair pbd peds opendata bulk data download patent information research search
Platform: UNKNOWN
Classifier: Development Status :: 3 - Alpha
Classifier: Environment :: Console
Classifier: Environment :: Web Environment
Classifier: Intended Audience :: Developers
Classifier: Intended Audience :: Education
Classifier: Intended Audience :: End Users/Desktop
Classifier: Intended Audience :: Information Technology
Classifier: Intended Audience :: Legal Industry
Classifier: Intended Audience :: Manufacturing
Classifier: Intended Audience :: Science/Research
Classifier: License :: OSI Approved :: MIT License
Classifier: Natural Language :: English
Classifier: Operating System :: MacOS :: MacOS X
Classifier: Operating System :: POSIX :: Linux
Classifier: Programming Language :: Python
Classifier: Topic :: Internet :: WWW/HTTP
Classifier: Topic :: Scientific/Engineering
Classifier: Topic :: Software Development :: Libraries
Classifier: Topic :: System :: Archiving
Classifier: Topic :: Text Processing
Classifier: Topic :: Utilities
Provides-Extra: release
Provides-Extra: documentation
